fwrlm/__init__.py
fwrlm/base.py
fwrlm/config.py
fwrlm/fwrlm.py
fwrlm/version.py
fwrlm/cli/__init__.py
fwrlm/cli/fwrlm_run.py
fwrlm/cli/render_run.py
fwrlm/cli/ssh_forward_run.py
fwrlm/utils/README
fwrlm/utils/__init__.py
fwrlm/utils/env_modules_python.py
fwrlm/utils/paramiko_forward.py
fwrlm/utils/render.py
fwrlm/utils/ssh_forward.py
fwrlm-0.1.2.dist-info/LICENSE
fwrlm-0.1.2.dist-info/METADATA
fwrlm-0.1.2.dist-info/WHEEL
fwrlm-0.1.2.dist-info/entry_points.txt
fwrlm-0.1.2.dist-info/top_level.txt
fwrlm-0.1.2.dist-info/RECORD
