Metadata-Version: 2.1
Name: fwrlm
Version: 0.1.2
Summary: FireWorks RocketLauncher Manager
Home-page: https://github.com/jotelha/fwrlm
Author: Johannes Laurin Hörmann
Author-email: johannes.hoermann@imtek.uni-freiburg.de
License: MIT
Download-URL: https://github.com/jotelha/fwrlm/tarball/0.1.2
Platform: UNKNOWN
Requires-Python: >=3.6.5
Requires-Dist: ansible (>=2.9.1)
Requires-Dist: fireworks (>=1.9.5)
Requires-Dist: jinja2 (>=2.10)
Requires-Dist: jinja2-time (>=0.2.0)
Requires-Dist: monty (>=4.0.2)
Requires-Dist: paramiko (>=2.4.2)
Requires-Dist: python-daemon (>=2.2.4)
Requires-Dist: pid (>=3.0.0)
Requires-Dist: psutil (>=5.6.1)
Requires-Dist: tabulate (>=0.8.2)
